__init__.py
cli.py
lib/exercise.py
tapps/exercise/ast.py
tapps/exercise/dict.py
tapps/exercise/eval.py
tapps/exercise/func_decorator.py
tapps/exercise/hello_world.py
tapps/exercise/lib_cli_opt.py
tapps/exercise/lib_context.py
tapps/exercise/lib_diff.py
tapps/exercise/lib_gitlab_api.py
tapps/exercise/lib_tfile.py
tapps/exercise/lib_thpe.py
tapps/exercise/lib_tssh.py
tapps/exercise/lib_ttemplate.py
tapps/exercise/lib_vilink.py
tapps/exercise/list.py
tapps/exercise/log4j.py
tapps/exercise/new_features.py
tapps/exercise/os.py
tapps/exercise/regexp.py
tapps/exercise/str.py
tapps/exercise/type.py
tio/__init__.py
tio/tcli.py
tio/tfile.py
tio/tshell.py
tlog/__init__.py
tlog/log4j.py
tlog/tlogging.py
tutils/cli_opt.py
tutils/context_opt.py
tutils/dynmic_module.py
tutils/inspectutils.py
tutils/tgitlab_api.py
tutils/thpe.py
tutils/tldap_api.py
tutils/tplugin_installer.py
tutils/tpython_mock.py
tutils/tssh.py
tutils/tstr.py
tutils/tsyno_server_api.py
tutils/ttemplate.py
tutils/tvault_api.py
tutils/tworkaround.py
scm_python_core-1.3.0.dev0.dist-info/METADATA
scm_python_core-1.3.0.dev0.dist-info/WHEEL
scm_python_core-1.3.0.dev0.dist-info/entry_points.txt
scm_python_core-1.3.0.dev0.dist-info/top_level.txt
scm_python_core-1.3.0.dev0.dist-info/RECORD
