Metadata-Version: 2.4
Name: scm-python-core
Version: 1.3.0.dev0
Summary: An core plugin Python project to use cli manage it
Author-email: "Shao,ShunZhong" <tempestwin@163.com>
Project-URL: Homepage, https://de.vicp.net:58443/Shao/scm-python-core
Requires-Python: >=3.9
Requires-Dist: pyyaml
Requires-Dist: ping3
Requires-Dist: paramiko
Requires-Dist: scp
Requires-Dist: jproperties
Requires-Dist: pyquery
Requires-Dist: requests
Requires-Dist: xpinyin
Requires-Dist: apscheduler
Requires-Dist: chardet
Requires-Dist: xmltodict
Requires-Dist: setuptools
Requires-Dist: Levenshtein
